{"name":"Register on the Utest.com page","id":"join-the-community-of-testers.;register-on-the-utest.com-page","testSteps":[{"number":1,"description":"Given than Carlos is on the Utest page","duration":8141,"startTime":"2022-10-05T14:52:29.153-05:00[America/Bogota]","screenshots":[{"screenshot":"e50f50fdb47322d46bf8de88f81728354d3d8ab40d00b13360a69b1765a9acb1.png","timeStamp":1664999557294}],"result":"SUCCESS","precondition":false,"level":0,"lineNumber":0,"children":[{"number":2,"description":"Carlos open up","duration":7105,"startTime":"2022-10-05T14:52:29.847-05:00[America/Bogota]","screenshots":[{"screenshot":"ac8a7773d717ef5e311e181c6bd59c92f542d4f1c8c27660bec20cafa11ce381.png","timeStamp":1664999556952}],"result":"SUCCESS","precondition":false,"level":1,"lineNumber":0,"children":[{"number":3,"description":"Carlos opens the Utest page","duration":7041,"startTime":"2022-10-05T14:52:29.881-05:00[America/Bogota]","screenshots":[{"screenshot":"ac8a7773d717ef5e311e181c6bd59c92f542d4f1c8c27660bec20cafa11ce381.png","timeStamp":1664999556921}],"result":"SUCCESS","precondition":false,"level":2,"lineNumber":0}]}]},{"number":4,"description":"When he clicks Join Today on the Utest page","duration":1061,"startTime":"2022-10-05T14:52:37.296-05:00[America/Bogota]","screenshots":[{"screenshot":"bc3eb9d1c3e57c007dbb51a0a56002771797841d7167609becb79d4ce9c17d64.png","timeStamp":1664999558356}],"result":"SUCCESS","precondition":false,"level":0,"lineNumber":0,"children":[{"number":5,"description":"Carlos join today","duration":766,"startTime":"2022-10-05T14:52:37.308-05:00[America/Bogota]","screenshots":[{"screenshot":"e75af2777ce9cb62dca8af1dcd3fd9d793dd37108f6c232aca21dd526ce6b392.png","timeStamp":1664999558073}],"result":"SUCCESS","precondition":false,"level":1,"lineNumber":0,"children":[{"number":6,"description":"Carlos clicks on Click in the button Join Today","duration":720,"startTime":"2022-10-05T14:52:37.317-05:00[America/Bogota]","screenshots":[{"screenshot":"e75af2777ce9cb62dca8af1dcd3fd9d793dd37108f6c232aca21dd526ce6b392.png","timeStamp":1664999558037}],"result":"SUCCESS","precondition":false,"level":2,"lineNumber":0}]}]},{"number":7,"description":"And he enters the data required in the four registration steps\r\n| first_name | last_name | email_address | month_bird | day_bird | year_bird | language | city | postal_code | country | computer | version | language_computer | mobile_device | model | operating_system | password | repeat_password |\r\n| Carlos | Castro | castro@correo.com | December | 3 | 1997 | Spanish | Bello, Antioquia | 050044 | Colombia | Windows | Windows 10 Education | Spanish | Motorola | Moto G9 Plus | Android 10 | Asdfghjkl123*a | Asdfghjkl123*a |","duration":9548,"startTime":"2022-10-05T14:52:38.358-05:00[America/Bogota]","exception":{"errorType":"org.openqa.selenium.NoSuchWindowException","message":"no such window: target window already closed\nfrom unknown error: web view not found\n  (Session info: chrome\u003d105.0.5195.127)\nBuild info: version: \u00273.141.59\u0027, revision: \u0027e82be7d358\u0027, time: \u00272018-11-14T08:17:03\u0027\nSystem info: host: \u0027CHMEPPF0FQ31E\u0027, ip: \u0027192.168.1.52\u0027, os.name: \u0027Windows 10\u0027, os.arch: \u0027amd64\u0027, os.version: \u002710.0\u0027, java.version: \u00271.8.0_341\u0027\nDriver info: org.openqa.selenium.chrome.ChromeDriver\nCapabilities {acceptInsecureCerts: false, browserName: chrome, browserVersion: 105.0.5195.127, chrome: {chromedriverVersion: 105.0.5195.19 (b9c217c128c1..., userDataDir: C:\\Users\\CCASTR~1\\AppData\\L...}, goog:chromeOptions: {debuggerAddress: localhost:57196}, javascriptEnabled: true, networkConnectionEnabled: false, pageLoadStrategy: normal, platform: WINDOWS, platformName: WINDOWS, proxy: Proxy(), setWindowRect: true, strictFileInteractability: false, timeouts: {implicit: 0, pageLoad: 300000, script: 30000}, unhandledPromptBehavior: dismiss and notify, webauthn:extension:credBlob: true, webauthn:extension:largeBlob: true, webauthn:virtualAuthenticators: true}\nSession ID: 8796faa855f33fdaeb64b3fc9fff5559\n*** Element info: {Using\u003dxpath, value\u003d//*[@id\u003d\"city\"]}","stackTrace":[{"declaringClass":"tasks.EntersTwo","methodName":"performAs","fileName":"EntersTwo.java","lineNumber":30},{"declaringClass":"stepdefinitions.UtestStepDefinition","methodName":"heEntersTheDataRequiredInTheFourRegistrationSteps","fileName":"UtestStepDefinition.java","lineNumber":32},{"declaringClass":"cucumber.runner.Runner","methodName":"runPickle","fileName":"Runner.java","lineNumber":80},{"declaringClass":"worker.org.gradle.process.internal.worker.GradleWorkerMain","methodName":"run","fileName":"GradleWorkerMain.java","lineNumber":69},{"declaringClass":"worker.org.gradle.process.internal.worker.GradleWorkerMain","methodName":"main","fileName":"GradleWorkerMain.java","lineNumber":74}]},"result":"ERROR","precondition":false,"level":0,"lineNumber":0,"children":[{"number":8,"description":"Carlos enters","duration":6456,"startTime":"2022-10-05T14:52:38.418-05:00[America/Bogota]","screenshots":[{"screenshot":"64e11884a440aad0c195ac0ab624c57a3797846e55039568d22bee88017f8eed.png","timeStamp":1664999564874}],"result":"SUCCESS","precondition":false,"level":1,"lineNumber":0,"children":[{"number":9,"description":"Carlos enters \u0027Carlos\u0027 into Where we write the first name","duration":717,"startTime":"2022-10-05T14:52:38.501-05:00[America/Bogota]","screenshots":[{"screenshot":"dcbe795ec06b5e7ba4c0f659936fcfed8026383771b15897035141cb1fa4da94.png","timeStamp":1664999559217}],"result":"SUCCESS","precondition":false,"level":2,"lineNumber":0},{"number":10,"description":"Carlos enters \u0027Castro\u0027 into Where we write the last name","duration":653,"startTime":"2022-10-05T14:52:39.220-05:00[America/Bogota]","screenshots":[{"screenshot":"fa05759bdf0b98876ebb17427573038452d38e7149ec57cf562ca0dd163eaef4.png","timeStamp":1664999559873}],"result":"SUCCESS","precondition":false,"level":2,"lineNumber":0},{"number":11,"description":"Carlos enters \u0027castro@correo.com\u0027 into Where we write the email address","duration":923,"startTime":"2022-10-05T14:52:39.875-05:00[America/Bogota]","screenshots":[{"screenshot":"74bf079ecee72aeb4bf4277ef0d20d1faa3957b591e92b1d8085a76e29ad9624.png","timeStamp":1664999560798}],"result":"SUCCESS","precondition":false,"level":2,"lineNumber":0},{"number":12,"description":"Carlos select December on Click on the month of date birth","duration":620,"startTime":"2022-10-05T14:52:40.801-05:00[America/Bogota]","screenshots":[{"screenshot":"425e38f9a7b5785fe93789fe8d5f33de36d19cfcff35462750bb7a1c8aa3be59.png","timeStamp":1664999561421}],"result":"SUCCESS","precondition":false,"level":2,"lineNumber":0},{"number":13,"description":"Carlos select 3 on Click on the day of date birth","duration":614,"startTime":"2022-10-05T14:52:41.423-05:00[America/Bogota]","screenshots":[{"screenshot":"c124bb2447214006f00798254cc739d4fef98588f04a2ec356b233d3e0cf2d26.png","timeStamp":1664999562037}],"result":"SUCCESS","precondition":false,"level":2,"lineNumber":0},{"number":14,"description":"Carlos select 1997 on Click on the year of date birth","duration":604,"startTime":"2022-10-05T14:52:42.040-05:00[America/Bogota]","screenshots":[{"screenshot":"f3e3fd670bfbe69eabad830382e61fa6def3838b7b3cc96156f25345e159eb14.png","timeStamp":1664999562644}],"result":"SUCCESS","precondition":false,"level":2,"lineNumber":0},{"number":15,"description":"Carlos enters \u0027Spanish\u0027 into Where we write the native language","duration":1123,"startTime":"2022-10-05T14:52:42.646-05:00[America/Bogota]","screenshots":[{"screenshot":"635bef09df85f31239d4d533106a5608341127de48d4575f2f726d3c5e5aecca.png","timeStamp":1664999563768}],"result":"SUCCESS","precondition":false,"level":2,"lineNumber":0},{"number":16,"description":"Carlos types \u0027ENTER\u0027 in Where we write the native language","duration":419,"startTime":"2022-10-05T14:52:43.770-05:00[America/Bogota]","screenshots":[{"screenshot":"635da138fde45ce0ca8ac9449a1948d7118ab2eac71616fe72ffa04f0f31454d.png","timeStamp":1664999564189}],"result":"SUCCESS","precondition":false,"level":2,"lineNumber":0},{"number":17,"description":"Carlos clicks on Click on the button for the steps next","duration":669,"startTime":"2022-10-05T14:52:44.191-05:00[America/Bogota]","screenshots":[{"screenshot":"64e11884a440aad0c195ac0ab624c57a3797846e55039568d22bee88017f8eed.png","timeStamp":1664999564860}],"result":"SUCCESS","precondition":false,"level":2,"lineNumber":0}]},{"number":18,"description":"Carlos enters two","duration":3011,"startTime":"2022-10-05T14:52:44.876-05:00[America/Bogota]","exception":{"errorType":"org.openqa.selenium.NoSuchWindowException","message":"no such window: target window already closed\nfrom unknown error: web view not found\n  (Session info: chrome\u003d105.0.5195.127)\nBuild info: version: \u00273.141.59\u0027, revision: \u0027e82be7d358\u0027, time: \u00272018-11-14T08:17:03\u0027\nSystem info: host: \u0027CHMEPPF0FQ31E\u0027, ip: \u0027192.168.1.52\u0027, os.name: \u0027Windows 10\u0027, os.arch: \u0027amd64\u0027, os.version: \u002710.0\u0027, java.version: \u00271.8.0_341\u0027\nDriver info: org.openqa.selenium.chrome.ChromeDriver\nCapabilities {acceptInsecureCerts: false, browserName: chrome, browserVersion: 105.0.5195.127, chrome: {chromedriverVersion: 105.0.5195.19 (b9c217c128c1..., userDataDir: C:\\Users\\CCASTR~1\\AppData\\L...}, goog:chromeOptions: {debuggerAddress: localhost:57196}, javascriptEnabled: true, networkConnectionEnabled: false, pageLoadStrategy: normal, platform: WINDOWS, platformName: WINDOWS, proxy: Proxy(), setWindowRect: true, strictFileInteractability: false, timeouts: {implicit: 0, pageLoad: 300000, script: 30000}, unhandledPromptBehavior: dismiss and notify, webauthn:extension:credBlob: true, webauthn:extension:largeBlob: true, webauthn:virtualAuthenticators: true}\nSession ID: 8796faa855f33fdaeb64b3fc9fff5559\n*** Element info: {Using\u003dxpath, value\u003d//*[@id\u003d\"city\"]}","stackTrace":[{"declaringClass":"tasks.EntersTwo","methodName":"performAs","fileName":"EntersTwo.java","lineNumber":30},{"declaringClass":"stepdefinitions.UtestStepDefinition","methodName":"heEntersTheDataRequiredInTheFourRegistrationSteps","fileName":"UtestStepDefinition.java","lineNumber":32},{"declaringClass":"cucumber.runner.Runner","methodName":"runPickle","fileName":"Runner.java","lineNumber":80},{"declaringClass":"worker.org.gradle.process.internal.worker.GradleWorkerMain","methodName":"run","fileName":"GradleWorkerMain.java","lineNumber":69},{"declaringClass":"worker.org.gradle.process.internal.worker.GradleWorkerMain","methodName":"main","fileName":"GradleWorkerMain.java","lineNumber":74}]},"result":"ERROR","precondition":false,"level":1,"lineNumber":0,"children":[{"number":19,"description":"Carlos clicks on Where we write the city","duration":920,"startTime":"2022-10-05T14:52:44.964-05:00[America/Bogota]","screenshots":[{"screenshot":"0584c431f64a3d55c61aa7265afe6cd15952523f5f8d53988e1964b59c1c4918.png","timeStamp":1664999565884}],"result":"SUCCESS","precondition":false,"level":2,"lineNumber":0},{"number":20,"description":"Carlos clears field Where we write the city","duration":506,"startTime":"2022-10-05T14:52:45.887-05:00[America/Bogota]","screenshots":[{"screenshot":"bb54dcac67281382ed4724dc42fd7554319c6775257fcddaba1de13f753e4e13.png","timeStamp":1664999566393}],"result":"SUCCESS","precondition":false,"level":2,"lineNumber":0},{"number":21,"description":"Carlos enters \u0027Bello, Antioquia\u0027 into Where we write the city","duration":810,"startTime":"2022-10-05T14:52:46.395-05:00[America/Bogota]","screenshots":[{"screenshot":"404b4ce6de63202153b31087b49065abc4141aaf43379547e62ebe5121a10a04.png","timeStamp":1664999567205}],"result":"SUCCESS","precondition":false,"level":2,"lineNumber":0},{"number":22,"description":"Carlos types \u0027DOWN\u0027 in Where we write the city","duration":551,"startTime":"2022-10-05T14:52:47.206-05:00[America/Bogota]","screenshots":[{"screenshot":"d335a279bf5740cf97c4d8d47645ddab2bbbcf49ef7475de1d4ef64de2fc33fd.png","timeStamp":1664999567757}],"result":"SUCCESS","precondition":false,"level":2,"lineNumber":0},{"number":23,"description":"Carlos types \u0027ENTER\u0027 in Where we write the city","duration":103,"startTime":"2022-10-05T14:52:47.760-05:00[America/Bogota]","exception":{"errorType":"org.openqa.selenium.NoSuchWindowException","message":"no such window: target window already closed\nfrom unknown error: web view not found\n  (Session info: chrome\u003d105.0.5195.127)\nBuild info: version: \u00273.141.59\u0027, revision: \u0027e82be7d358\u0027, time: \u00272018-11-14T08:17:03\u0027\nSystem info: host: \u0027CHMEPPF0FQ31E\u0027, ip: \u0027192.168.1.52\u0027, os.name: \u0027Windows 10\u0027, os.arch: \u0027amd64\u0027, os.version: \u002710.0\u0027, java.version: \u00271.8.0_341\u0027\nDriver info: org.openqa.selenium.chrome.ChromeDriver\nCapabilities {acceptInsecureCerts: false, browserName: chrome, browserVersion: 105.0.5195.127, chrome: {chromedriverVersion: 105.0.5195.19 (b9c217c128c1..., userDataDir: C:\\Users\\CCASTR~1\\AppData\\L...}, goog:chromeOptions: {debuggerAddress: localhost:57196}, javascriptEnabled: true, networkConnectionEnabled: false, pageLoadStrategy: normal, platform: WINDOWS, platformName: WINDOWS, proxy: Proxy(), setWindowRect: true, strictFileInteractability: false, timeouts: {implicit: 0, pageLoad: 300000, script: 30000}, unhandledPromptBehavior: dismiss and notify, webauthn:extension:credBlob: true, webauthn:extension:largeBlob: true, webauthn:virtualAuthenticators: true}\nSession ID: 8796faa855f33fdaeb64b3fc9fff5559\n*** Element info: {Using\u003dxpath, value\u003d//*[@id\u003d\"city\"]}","stackTrace":[{"declaringClass":"tasks.EntersTwo","methodName":"performAs","fileName":"EntersTwo.java","lineNumber":30},{"declaringClass":"stepdefinitions.UtestStepDefinition","methodName":"heEntersTheDataRequiredInTheFourRegistrationSteps","fileName":"UtestStepDefinition.java","lineNumber":32},{"declaringClass":"cucumber.runner.Runner","methodName":"runPickle","fileName":"Runner.java","lineNumber":80},{"declaringClass":"worker.org.gradle.process.internal.worker.GradleWorkerMain","methodName":"run","fileName":"GradleWorkerMain.java","lineNumber":69},{"declaringClass":"worker.org.gradle.process.internal.worker.GradleWorkerMain","methodName":"main","fileName":"GradleWorkerMain.java","lineNumber":74}]},"result":"ERROR","precondition":false,"level":2,"lineNumber":0}]}]},{"number":24,"description":"And he accept the terms of use, the guidelines and the privacy and security policy of utest","duration":4,"startTime":"2022-10-05T14:52:47.945-05:00[America/Bogota]","result":"SKIPPED","precondition":false,"level":0,"lineNumber":0},{"number":25,"description":"Then he registers successful on the Utest page seeing a message First, please check your email inbox","duration":4,"startTime":"2022-10-05T14:52:47.951-05:00[America/Bogota]","result":"SKIPPED","precondition":false,"level":0,"lineNumber":0}],"userStory":{"id":"join-the-community-of-testers.","storyName":"Join the community of testers.","path":"src/test/resources/features/utest.feature","narrative":"  As a user,I want to join to the world\u0027s largest community of testers on the Utes.com page","type":"feature"},"featureTag":{"name":"Features/Join the community of testers.","type":"feature","displayName":"Features/Join the community of testers."},"title":"Register on the Utest.com page","tags":[{"name":"case","type":"tag","displayName":"case"},{"name":"Join the community of testers.","type":"feature","displayName":"Join the community of testers."}],"startTime":"2022-10-05T14:52:28.979-05:00[America/Bogota]","duration":18981,"testFailureCause":{"errorType":"org.openqa.selenium.NoSuchWindowException","message":"no such window: target window already closed\nfrom unknown error: web view not found\n  (Session info: chrome\u003d105.0.5195.127)\nBuild info: version: \u00273.141.59\u0027, revision: \u0027e82be7d358\u0027, time: \u00272018-11-14T08:17:03\u0027\nSystem info: host: \u0027CHMEPPF0FQ31E\u0027, ip: \u0027192.168.1.52\u0027, os.name: \u0027Windows 10\u0027, os.arch: \u0027amd64\u0027, os.version: \u002710.0\u0027, java.version: \u00271.8.0_341\u0027\nDriver info: org.openqa.selenium.chrome.ChromeDriver\nCapabilities {acceptInsecureCerts: false, browserName: chrome, browserVersion: 105.0.5195.127, chrome: {chromedriverVersion: 105.0.5195.19 (b9c217c128c1..., userDataDir: C:\\Users\\CCASTR~1\\AppData\\L...}, goog:chromeOptions: {debuggerAddress: localhost:57196}, javascriptEnabled: true, networkConnectionEnabled: false, pageLoadStrategy: normal, platform: WINDOWS, platformName: WINDOWS, proxy: Proxy(), setWindowRect: true, strictFileInteractability: false, timeouts: {implicit: 0, pageLoad: 300000, script: 30000}, unhandledPromptBehavior: dismiss and notify, webauthn:extension:credBlob: true, webauthn:extension:largeBlob: true, webauthn:virtualAuthenticators: true}\nSession ID: 8796faa855f33fdaeb64b3fc9fff5559\n*** Element info: {Using\u003dxpath, value\u003d//*[@id\u003d\"city\"]}","stackTrace":[{"declaringClass":"tasks.EntersTwo","methodName":"performAs","fileName":"EntersTwo.java","lineNumber":30},{"declaringClass":"stepdefinitions.UtestStepDefinition","methodName":"heEntersTheDataRequiredInTheFourRegistrationSteps","fileName":"UtestStepDefinition.java","lineNumber":32},{"declaringClass":"cucumber.runner.Runner","methodName":"runPickle","fileName":"Runner.java","lineNumber":80},{"declaringClass":"worker.org.gradle.process.internal.worker.GradleWorkerMain","methodName":"run","fileName":"GradleWorkerMain.java","lineNumber":69},{"declaringClass":"worker.org.gradle.process.internal.worker.GradleWorkerMain","methodName":"main","fileName":"GradleWorkerMain.java","lineNumber":74}]},"testFailureClassname":"org.openqa.selenium.NoSuchWindowException","testFailureMessage":"no such window: target window already closed\nfrom unknown error: web view not found\n  (Session info: chrome\u003d105.0.5195.127)\nBuild info: version: \u00273.141.59\u0027, revision: \u0027e82be7d358\u0027, time: \u00272018-11-14T08:17:03\u0027\nSystem info: host: \u0027CHMEPPF0FQ31E\u0027, ip: \u0027192.168.1.52\u0027, os.name: \u0027Windows 10\u0027, os.arch: \u0027amd64\u0027, os.version: \u002710.0\u0027, java.version: \u00271.8.0_341\u0027\nDriver info: org.openqa.selenium.chrome.ChromeDriver\nCapabilities {acceptInsecureCerts: false, browserName: chrome, browserVersion: 105.0.5195.127, chrome: {chromedriverVersion: 105.0.5195.19 (b9c217c128c1..., userDataDir: C:\\Users\\CCASTR~1\\AppData\\L...}, goog:chromeOptions: {debuggerAddress: localhost:57196}, javascriptEnabled: true, networkConnectionEnabled: false, pageLoadStrategy: normal, platform: WINDOWS, platformName: WINDOWS, proxy: Proxy(), setWindowRect: true, strictFileInteractability: false, timeouts: {implicit: 0, pageLoad: 300000, script: 30000}, unhandledPromptBehavior: dismiss and notify, webauthn:extension:credBlob: true, webauthn:extension:largeBlob: true, webauthn:virtualAuthenticators: true}\nSession ID: 8796faa855f33fdaeb64b3fc9fff5559\n*** Element info: {Using\u003dxpath, value\u003d//*[@id\u003d\"city\"]}","testFailureSummary":"ERROR;org.openqa.selenium.NoSuchWindowException;no such window: target window already closed\nfrom unknown error: web view not found\n  (Session info: chrome\u003d105.0.5195.127)\nBuild info: version: \u00273.141.59\u0027, revision: \u0027e82be7d358\u0027, time: \u00272018-11-14T08:17:03\u0027\nSystem info: host: \u0027CHMEPPF0FQ31E\u0027, ip: \u0027192.168.1.52\u0027, os.name: \u0027Windows 10\u0027, os.arch: \u0027amd64\u0027, os.version: \u002710.0\u0027, java.version: \u00271.8.0_341\u0027\nDriver info: org.openqa.selenium.chrome.ChromeDriver\nCapabilities {acceptInsecureCerts: false, browserName: chrome, browserVersion: 105.0.5195.127, chrome: {chromedriverVersion: 105.0.5195.19 (b9c217c128c1..., userDataDir: C:\\Users\\CCASTR~1\\AppData\\L...}, goog:chromeOptions: {debuggerAddress: localhost:57196}, javascriptEnabled: true, networkConnectionEnabled: false, pageLoadStrategy: normal, platform: WINDOWS, platformName: WINDOWS, proxy: Proxy(), setWindowRect: true, strictFileInteractability: false, timeouts: {implicit: 0, pageLoad: 300000, script: 30000}, unhandledPromptBehavior: dismiss and notify, webauthn:extension:credBlob: true, webauthn:extension:largeBlob: true, webauthn:virtualAuthenticators: true}\nSession ID: 8796faa855f33fdaeb64b3fc9fff5559\n*** Element info: {Using\u003dxpath, value\u003d//*[@id\u003d\"city\"]};EntersTwo.java","projectKey":"","annotatedResult":"ERROR","sessionId":"8796faa855f33fdaeb64b3fc9fff5559","driver":"chrome:carlos","isManualTestingUpToDate":false,"manual":false,"testSource":"Cucumber","actors":[{"name":"Carlos","can":["browse the web"]}],"result":"ERROR"}